freetracker/__init__.py
freetracker/cli.py
freetracker/completion.py
freetracker/models.py
freetracker/storage.py
freetracker/ui.py
freetracker-0.2.0.dist-info/METADATA
freetracker-0.2.0.dist-info/WHEEL
freetracker-0.2.0.dist-info/entry_points.txt
freetracker-0.2.0.dist-info/licenses/LICENSE
freetracker-0.2.0.dist-info/RECORD
