Metadata-Version: 2.4
Name: freetracker
Version: 0.2.0
Summary: Basic work hour tracking tool for freelancers
Project-URL: Homepage, https://github.com/tensorturtle/freetracker
Project-URL: Repository, https://github.com/tensorturtle/freetracker
Project-URL: Issues, https://github.com/tensorturtle/freetracker/issues
Author-email: "Jason (Janghyup) Sohn" <tensorturtle@example.com>
License: MIT
License-File: LICENSE
Keywords: cli,freelance,productivity,time-tracking
Classifier: Development Status :: 4 - Beta
Classifier: Environment :: Console
Classifier: Intended Audience :: End Users/Desktop
Classifier: License :: OSI Approved :: MIT License
Classifier: Operating System :: OS Independent
Classifier: Programming Language :: Python :: 3
Classifier: Programming Language :: Python :: 3.12
Classifier: Topic :: Office/Business
Classifier: Topic :: Utilities
Requires-Python: >=3.12
Requires-Dist: click>=8.1.0
Requires-Dist: rich>=14.0.0
Requires-Dist: tinydb>=4.8.2
